interlatent/__init__.py
interlatent/hooks.py
interlatent/metrics.py
interlatent/schema.py
interlatent/analysis/__init__.py
interlatent/analysis/dataset/__init__.py
interlatent/analysis/dataset/activation_pair_dataset.py
interlatent/analysis/dataset/activation_vector_dataset.py
interlatent/analysis/dataset/linear_probe_dataset.py
interlatent/analysis/dataset/prompt_dataset.py
interlatent/analysis/intervention/__init__.py
interlatent/analysis/intervention/api.py
interlatent/analysis/intervention/latents.py
interlatent/analysis/intervention/patch.py
interlatent/analysis/models/__init__.py
interlatent/analysis/models/linear_probe.py
interlatent/analysis/models/linear_transcoder.py
interlatent/analysis/models/sae.py
interlatent/analysis/train/__init__.py
interlatent/analysis/train/linear_probe_trainer.py
interlatent/analysis/train/online_sae_trainer.py
interlatent/analysis/train/sae_pipeline.py
interlatent/analysis/train/sae_trainer.py
interlatent/analysis/train/transcoder_pipeline.py
interlatent/analysis/train/transcoder_trainer.py
interlatent/analysis/vis/__init__.py
interlatent/analysis/vis/diff.py
interlatent/analysis/vis/plot.py
interlatent/analysis/vis/search.py
interlatent/analysis/vis/summary.py
interlatent/api/__init__.py
interlatent/api/latent_db.py
interlatent/collectors/__init__.py
interlatent/collectors/gym_collector.py
interlatent/collectors/llm_collector.py
interlatent/storage/base.py
interlatent/storage/hdf5.py
interlatent/storage/hdf5_row.py
interlatent/storage/sqlite.py
interlatent/utils/hook_utils.py
interlatent/utils/logging.py
interlatent-0.1.8.dist-info/licenses/LICENSE
interlatent-0.1.8.dist-info/METADATA
interlatent-0.1.8.dist-info/WHEEL
interlatent-0.1.8.dist-info/top_level.txt
interlatent-0.1.8.dist-info/RECORD
