Metadata-Version: 2.4
Name: interlatent
Version: 0.1.8
Summary: Interpretability toolkit for collecting, storing, and analyzing activations.
Author: Interlatent Contributors
License: MIT
Project-URL: Homepage, https://github.com/seanpixel/interlatent
Project-URL: Issues, https://github.com/seanpixel/interlatent/issues
Classifier: Programming Language :: Python :: 3
Classifier: Programming Language :: Python :: 3.11
Classifier: License :: OSI Approved :: MIT License
Classifier: Operating System :: OS Independent
Classifier: Topic :: Scientific/Engineering :: Artificial Intelligence
Requires-Python: >=3.11
License-File: LICENSE
Requires-Dist: gymnasium==1.2.2
Requires-Dist: stable_baselines3==2.7.0
Requires-Dist: matplotlib==3.6.0
Requires-Dist: pydantic==2.12.5
Requires-Dist: pytest==7.1.1
Requires-Dist: h5py==3.11.0
Requires-Dist: datasets==4.4.1
Requires-Dist: transformers>=4.57.3
Requires-Dist: accelerate>=0.26.0
Requires-Dist: torch==2.9.1
Requires-Dist: torchvision==0.24.1
Requires-Dist: numpy==1.26.4
Provides-Extra: dev
Requires-Dist: torch==2.2.2; platform_machine != "arm64" and extra == "dev"
Requires-Dist: gymnasium; extra == "dev"
Requires-Dist: pytest; extra == "dev"
Dynamic: license-file
